pyextron/__init__.py
pyextron/config.py
pyextron/protocol.py
pyextron/protocols/mav88.yaml
pyextron/series/mav88.yaml
pyextron-0.0.1.dist-info/METADATA
pyextron-0.0.1.dist-info/WHEEL
pyextron-0.0.1.dist-info/top_level.txt
pyextron-0.0.1.dist-info/zip-safe
pyextron-0.0.1.dist-info/RECORD
