Metadata-Version: 2.1
Name: pyextron
Version: 0.0.1
Summary: Library for Telnet serial communication to Extron Media Switchers
Home-page: https://github.com/zombielinux/pyextron
Author: William Sutton
Author-email: will@sutton-family.org
License: MIT
Download-URL: https://github.com/zombielinux/pyextron/archive/0.0.1.tar.gz
Platform: UNKNOWN
Classifier: Development Status :: 4 - Beta
Classifier: License :: OSI Approved :: MIT License
Classifier: Programming Language :: Python :: 3
Requires-Dist: ratelimit (>=2.2.1)
